ai_puti-0.1.0b15.dist-info/licenses/LICENSE
puti/__init__.py
puti/bootstrap.py
puti/capture.py
puti/cli.py
puti/logs.py
puti/scheduler.py
puti/celery_queue/__init__.py
puti/celery_queue/celery_app.py
puti/celery_queue/producer.py
puti/celery_queue/simplified_tasks.py
puti/celery_queue/tasks.py
puti/client/__init__.py
puti/client/client.py
puti/client/client_resp.py
puti/client/lunar/__init__.py
puti/client/lunar/lunar_client.py
puti/client/telegram/__init__.py
puti/client/twitter/__init__.py
puti/client/twitter/twitter_client.py
puti/client/twitter/x_api.py
puti/conf/__init__.py
puti/conf/celery_config.py
puti/conf/celery_private_conf.py
puti/conf/client_config.py
puti/conf/config.py
puti/conf/config.yaml
puti/conf/llm_config.py
puti/conf/mysql_conf.py
puti/constant/__init__.py
puti/constant/base.py
puti/constant/client.py
puti/constant/llm.py
puti/constant/utilities.py
puti/core/__init__.py
puti/core/config_setup.py
puti/core/exception.py
puti/core/req.py
puti/core/resp.py
puti/db/__init__.py
puti/db/base_manager.py
puti/db/faisss.py
puti/db/mysql_operator.py
puti/db/schedule_manager.py
puti/db/sqlite_operator.py
puti/db/task_state_guard.py
puti/db/model/__init__.py
puti/db/model/system.py
puti/db/model/chat/__init__.py
puti/db/model/chat/chat.py
puti/db/model/client/__init__.py
puti/db/model/client/twitter.py
puti/db/model/task/__init__.py
puti/db/model/task/bot_task.py
puti/llm/__init__.py
puti/llm/cost.py
puti/llm/envs.py
puti/llm/memory.py
puti/llm/messages.py
puti/llm/nodes.py
puti/llm/workflow.py
puti/llm/actions/__init__.py
puti/llm/actions/alex.py
puti/llm/actions/x_bot.py
puti/llm/graph/__init__.py
puti/llm/graph/ethan_graph.py
puti/llm/prompts/__init__.py
puti/llm/roles/__init__.py
puti/llm/roles/agents.py
puti/llm/roles/x_bot.py
puti/llm/tools/__init__.py
puti/llm/tools/calculator.py
puti/llm/tools/common.py
puti/llm/tools/debate.py
puti/llm/tools/demo.py
puti/llm/tools/file.py
puti/llm/tools/generate_tweet.py
puti/llm/tools/project_analyzer.py
puti/llm/tools/python.py
puti/llm/tools/talk.py
ai_puti-0.1.0b15.dist-info/METADATA
ai_puti-0.1.0b15.dist-info/WHEEL
ai_puti-0.1.0b15.dist-info/entry_points.txt
ai_puti-0.1.0b15.dist-info/top_level.txt
ai_puti-0.1.0b15.dist-info/RECORD
