Metadata-Version: 2.4
Name: ai_puti
Version: 0.1.0b15
Summary: puti: MultiAgent-based package for LLM
Home-page: https://github.com/aivoyager/puti
Author: obstaclews
Author-email: obstaclesws@qq.com
Maintainer: obstaclews
Keywords: llm,multiagent,package,agent,twikit,openai,websearch,terminal,python,file,fastapi,mcp
Classifier: Programming Language :: Python :: 3
Classifier: License :: OSI Approved :: MIT License
Classifier: Operating System :: OS Independent
Requires-Python: >=3.10
License-File: LICENSE
Requires-Dist: wheel==0.45.1
Requires-Dist: ollama==0.5.1
Requires-Dist: click==8.2.1
Requires-Dist: pytest==8.4.0
Requires-Dist: googlesearch-python==1.3.0
Requires-Dist: scikit-learn==1.7.0
Requires-Dist: tiktoken==0.9.0
Requires-Dist: openai==1.84.0
Requires-Dist: mcp==1.9.3
Requires-Dist: anthropic==0.52.2
Requires-Dist: python-box==7.3.2
Requires-Dist: pyyaml==6.0.2
Requires-Dist: faiss-cpu==1.11.0
Requires-Dist: pandas==2.3.0
Requires-Dist: jinja2==3.1.6
Requires-Dist: twikit==2.3.3
Requires-Dist: pytest-asyncio==1.0.0
Requires-Dist: pydantic==2.10.6
Requires-Dist: questionary==2.0.1
Requires-Dist: rich==13.7.1
Requires-Dist: python-dotenv==1.0.1
Requires-Dist: numpy==2.3.0
Requires-Dist: numexpr==2.11.0
Requires-Dist: celery==5.5.3
Requires-Dist: tenacity==9.1.2
Requires-Dist: croniter==2.0.2
Requires-Dist: pymysql==1.1.1
Requires-Dist: loguru==0.7.3
Dynamic: author
Dynamic: author-email
Dynamic: classifier
Dynamic: description
Dynamic: description-content-type
Dynamic: home-page
Dynamic: keywords
Dynamic: license-file
Dynamic: maintainer
Dynamic: requires-dist
Dynamic: requires-python
Dynamic: summary
